{
  "bot_states": [
    {
      "ID": 0,
      "direction": 35.609717787423584,
      "state": {},
      "x_position": 254.16092601395724,
      "y_position": -150.70577583309762
    },
    {
      "ID": 1,
      "direction": -1.1736990447082585,
      "state": {},
      "x_position": -102.99578404387657,
      "y_position": -116.09035508955344
    },
    {
      "ID": 2,
      "direction": 63.364791831048912,
      "state": {},
      "x_position": 248.07581628274869,
      "y_position": 221.76586035986423
    },
    {
      "ID": 3,
      "direction": 30.739082244331076,
      "state": {},
      "x_position": 114.31359446132586,
      "y_position": -306.1416710967988
    },
    {
      "ID": 4,
      "direction": -32.392513531386378,
      "state": {},
      "x_position": -88.328898760577928,
      "y_position": 5.1731289699397038
    },
    {
      "ID": 5,
      "direction": -37.367966360087685,
      "state": {},
      "x_position": -162.34480171757002,
      "y_position": -48.356391280087891
    },
    {
      "ID": 6,
      "direction": 26.67705869856232,
      "state": {},
      "x_position": 49.808058848255584,
      "y_position": -45.219364154801212
    },
    {
      "ID": 7,
      "direction": -16.732089257330962,
      "state": {},
      "x_position": 73.147893727029242,
      "y_position": 13.253466409300916
    },
    {
      "ID": 8,
      "direction": 10.693745972388669,
      "state": {},
      "x_position": 12.566225899178619,
      "y_position": -138.08007130345862
    },
    {
      "ID": 9,
      "direction": 68.384563321340465,
      "state": {},
      "x_position": 5.5285385691761668,
      "y_position": 28.268087852978876
    },
    {
      "ID": 10,
      "direction": 16.89812231626733,
      "state": {},
      "x_position": -330.40303641752536,
      "y_position": 327.40382132206878
    },
    {
      "ID": 11,
      "direction": -19.007746658477981,
      "state": {},
      "x_position": 652.95884904293587,
      "y_position": -48.769351060507532
    },
    {
      "ID": 12,
      "direction": 21.759624869431558,
      "state": {},
      "x_position": 528.31853887783075,
      "y_position": 249.37876878875548
    },
    {
      "ID": 13,
      "direction": 50.991224971415768,
      "state": {},
      "x_position": 396.60469169180237,
      "y_position": 138.00177147750998
    },
    {
      "ID": 14,
      "direction": -7.274301923802426,
      "state": {},
      "x_position": 47.981431039506823,
      "y_position": -79.792645434094226
    },
    {
      "ID": 15,
      "direction": 6.7488477303221881,
      "state": {},
      "x_position": -167.62949191159922,
      "y_position": 250.22835556128857
    },
    {
      "ID": 16,
      "direction": -22.64489234416887,
      "state": {},
      "x_position": -296.82870365616031,
      "y_position": -50.287917222439432
    },
    {
      "ID": 17,
      "direction": 35.458494578557641,
      "state": {},
      "x_position": 28.09720158531886,
      "y_position": 205.09620871646894
    },
    {
      "ID": 18,
      "direction": 33.488502941503462,
      "state": {},
      "x_position": -241.59949557091278,
      "y_position": -231.18126196135
    },
    {
      "ID": 19,
      "direction": 20.694625085556346,
      "state": {},
      "x_position": -235.36040178245867,
      "y_position": 135.96949869045051
    },
    {
      "ID": 20,
      "direction": -11.498116779088411,
      "state": {},
      "x_position": -206.15395039765258,
      "y_position": 117.14480345043478
    },
    {
      "ID": 21,
      "direction": 25.645113572720668,
      "state": {},
      "x_position": 58.413073545863462,
      "y_position": 185.96455341878982
    },
    {
      "ID": 22,
      "direction": -48.530224695747641,
      "state": {},
      "x_position": -301.91294661642183,
      "y_position": 197.36607413041403
    },
    {
      "ID": 23,
      "direction": -14.287058555659337,
      "state": {},
      "x_position": 190.7008750319925,
      "y_position": 527.62909609628389
    },
    {
      "ID": 24,
      "direction": 9.0027874626030631,
      "state": {},
      "x_position": -16.075076452109183,
      "y_position": 377.42900270483022
    },
    {
      "ID": 25,
      "direction": -29.892131248073934,
      "state": {},
      "x_position": 29.717349230564597,
      "y_position": 676.47761864234405
    },
    {
      "ID": 26,
      "direction": -11.108193067584521,
      "state": {},
      "x_position": 60.117629897240469,
      "y_position": -116.40338958215973
    },
    {
      "ID": 27,
      "direction": 85.166035340658468,
      "state": {},
      "x_position": 425.44671472414814,
      "y_position": 119.87676911933086
    },
    {
      "ID": 28,
      "direction": -84.812781729305811,
      "state": {},
      "x_position": -40.991702483563635,
      "y_position": 220.47173201008914
    },
    {
      "ID": 29,
      "direction": 5.7340089125671234,
      "state": {},
      "x_position": 413.50211027321183,
      "y_position": 269.09755234317038
    },
    {
      "ID": 30,
      "direction": -25.944985441081602,
      "state": {},
      "x_position": 156.24236697216674,
      "y_position": 70.138963683485031
    },
    {
      "ID": 31,
      "direction": 20.222252924781429,
      "state": {},
      "x_position": 381.53117260297671,
      "y_position": -42.241945440203331
    },
    {
      "ID": 32,
      "direction": -2.7037930078592183,
      "state": {},
      "x_position": -185.3662986137945,
      "y_position": -468.45623661144924
    },
    {
      "ID": 33,
      "direction": 0.24879554114505664,
      "state": {},
      "x_position": -245.31443315002929,
      "y_position": 265.38275658732357
    },
    {
      "ID": 34,
      "direction": 76.088691250360995,
      "state": {},
      "x_position": -92.32141587181998,
      "y_position": 81.983627200130258
    },
    {
      "ID": 35,
      "direction": 90.358631932240385,
      "state": {},
      "x_position": -21.783179074182264,
      "y_position": 48.969851564114535
    },
    {
      "ID": 36,
      "direction": 17.155714182194274,
      "state": {},
      "x_position": -347.13836419994266,
      "y_position": 163.38006827949903
    },
    {
      "ID": 37,
      "direction": 12.932826194099004,
      "state": {},
      "x_position": -203.11328672848563,
      "y_position": 176.51166530112224
    },
    {
      "ID": 38,
      "direction": -38.064135917438996,
      "state": {},
      "x_position": -270.48979680647255,
      "y_position": 322.14460153179465
    },
    {
      "ID": 39,
      "direction": 15.747775380525354,
      "state": {},
      "x_position": -237.74042624090856,
      "y_position": 5.9032539742621566
    },
    {
      "ID": 40,
      "direction": -36.284655927978974,
      "state": {},
      "x_position": 112.58576457365139,
      "y_position": 59.576720761473887
    },
    {
      "ID": 41,
      "direction": 7.2534617969029256,
      "state": {},
      "x_position": 155.02441103156963,
      "y_position": -104.37955015021234
    },
    {
      "ID": 42,
      "direction": -61.249397633478203,
      "state": {},
      "x_position": 19.715570692971472,
      "y_position": 481.23481321059512
    },
    {
      "ID": 43,
      "direction": -53.561956666184621,
      "state": {},
      "x_position": 303.02611392764095,
      "y_position": 47.933053038048961
    },
    {
      "ID": 44,
      "direction": 44.749209526104913,
      "state": {},
      "x_position": 100.12539222498972,
      "y_position": 314.95046581005425
    },
    {
      "ID": 45,
      "direction": -37.119312669994308,
      "state": {},
      "x_position": -83.695480689614953,
      "y_position": -307.05701223379066
    },
    {
      "ID": 46,
      "direction": 29.828469475365434,
      "state": {},
      "x_position": 189.81740270154353,
      "y_position": 77.767711976745787
    },
    {
      "ID": 47,
      "direction": 4.0127942693024226,
      "state": {},
      "x_position": 141.93539523538155,
      "y_position": 230.41413069408173
    },
    {
      "ID": 48,
      "direction": 24.324025266406885,
      "state": {},
      "x_position": 161.36783633871408,
      "y_position": 166.75070389393724
    },
    {
      "ID": 49,
      "direction": -6.3454107200979557,
      "state": {},
      "x_position": 535.76492565954152,
      "y_position": -302.76799649147614
    },
    {
      "ID": 50,
      "direction": 27.176139151873098,
      "state": {},
      "x_position": 297.40069888145842,
      "y_position": -74.326361203732262
    },
    {
      "ID": 51,
      "direction": 12.160081591954871,
      "state": {},
      "x_position": 421.53480153815553,
      "y_position": 192.7059552904783
    },
    {
      "ID": 52,
      "direction": -24.172075172196749,
      "state": {},
      "x_position": 181.26080465251107,
      "y_position": 32.931012423185066
    },
    {
      "ID": 53,
      "direction": -16.933639843803032,
      "state": {},
      "x_position": 164.88317218102782,
      "y_position": -586.15035546379863
    },
    {
      "ID": 54,
      "direction": 11.531909134803598,
      "state": {},
      "x_position": 43.230285486328832,
      "y_position": -612.29557035283335
    },
    {
      "ID": 55,
      "direction": 31.624720831409331,
      "state": {},
      "x_position": 156.21608313961517,
      "y_position": -149.37783058153599
    },
    {
      "ID": 56,
      "direction": -7.1666750073145735,
      "state": {},
      "x_position": -72.69067455546751,
      "y_position": -340.58071156887149
    },
    {
      "ID": 57,
      "direction": 2.6685223186852229,
      "state": {},
      "x_position": -48.571963371334604,
      "y_position": -105.98420970436948
    },
    {
      "ID": 58,
      "direction": 21.280936988618329,
      "state": {},
      "x_position": -263.55840478861182,
      "y_position": -377.82195614775168
    },
    {
      "ID": 59,
      "direction": 30.282905387037356,
      "state": {},
      "x_position": -125.16122325625955,
      "y_position": 9.8630616578599337
    },
    {
      "ID": 60,
      "direction": -43.042998020261628,
      "state": {},
      "x_position": 107.23172830733861,
      "y_position": 25.6533544974384
    },
    {
      "ID": 61,
      "direction": 5.3067908029374617,
      "state": {},
      "x_position": -343.26483048097208,
      "y_position": -182.22537446439139
    },
    {
      "ID": 62,
      "direction": 2.5141205954073964,
      "state": {},
      "x_position": -265.80997587952169,
      "y_position": 96.696976264629299
    },
    {
      "ID": 63,
      "direction": 83.642973637608478,
      "state": {},
      "x_position": -217.84915483007029,
      "y_position": -321.14425933333081
    },
    {
      "ID": 64,
      "direction": -37.557189900007629,
      "state": {},
      "x_position": -590.36373828272201,
      "y_position": -145.89766406350572
    },
    {
      "ID": 65,
      "direction": 16.981143870759755,
      "state": {},
      "x_position": -437.5312461641355,
      "y_position": 243.54794485335543
    },
    {
      "ID": 66,
      "direction": 47.889752661849748,
      "state": {},
      "x_position": -231.13096501655994,
      "y_position": -85.887933491815957
    },
    {
      "ID": 67,
      "direction": -27.757866300939149,
      "state": {},
      "x_position": -538.24838469763699,
      "y_position": -61.751147521062514
    },
    {
      "ID": 68,
      "direction": 39.286990984777617,
      "state": {},
      "x_position": 22.792509931158357,
      "y_position": 239.22092659268992
    },
    {
      "ID": 69,
      "direction": -34.119808434908578,
      "state": {},
      "x_position": -570.10052368674928,
      "y_position": 453.10657932404655
    },
    {
      "ID": 70,
      "direction": 5.0725517861446594,
      "state": {},
      "x_position": -145.81300387560873,
      "y_position": 95.968375828374406
    },
    {
      "ID": 71,
      "direction": 35.010408190183938,
      "state": {},
      "x_position": 72.969988621890536,
      "y_position": 338.20984639186099
    },
    {
      "ID": 72,
      "direction": 24.413709673136044,
      "state": {},
      "x_position": -173.59632535816814,
      "y_position": 348.30294823792684
    },
    {
      "ID": 73,
      "direction": 63.822808630490371,
      "state": {},
      "x_position": -160.65867153253026,
      "y_position": 8.9694106106228322
    },
    {
      "ID": 74,
      "direction": 4.1342923846297097,
      "state": {},
      "x_position": 135.18075735629441,
      "y_position": 645.26176370981761
    },
    {
      "ID": 75,
      "direction": 24.921129290629828,
      "state": {},
      "x_position": 278.31300688186622,
      "y_position": 399.53867145385988
    },
    {
      "ID": 76,
      "direction": 37.958128142947118,
      "state": {},
      "x_position": 191.54381445549663,
      "y_position": 663.75812583180198
    },
    {
      "ID": 77,
      "direction": 18.377854808490618,
      "state": {},
      "x_position": 160.30877758394996,
      "y_position": 201.30996946922005
    },
    {
      "ID": 78,
      "direction": -42.224786399698516,
      "state": {},
      "x_position": -75.204375144554433,
      "y_position": 229.3160007650371
    },
    {
      "ID": 79,
      "direction": -1.8125769483469645,
      "state": {},
      "x_position": 195.7874846397749,
      "y_position": 113.22057608028494
    },
    {
      "ID": 80,
      "direction": 79.613910753146001,
      "state": {},
      "x_position": 225.48319555890254,
      "y_position": 375.45193888679006
    },
    {
      "ID": 81,
      "direction": -15.207743701972952,
      "state": {},
      "x_position": 107.27385722622434,
      "y_position": 119.17823357032258
    },
    {
      "ID": 82,
      "direction": 23.926308753676668,
      "state": {},
      "x_position": 102.14259594974359,
      "y_position": -226.46302849359859
    },
    {
      "ID": 83,
      "direction": -51.666363497569392,
      "state": {},
      "x_position": 288.51552981255224,
      "y_position": -31.53826407490974
    },
    {
      "ID": 84,
      "direction": -78.155156170625588,
      "state": {},
      "x_position": 562.82782611918776,
      "y_position": -338.5584869636898
    },
    {
      "ID": 85,
      "direction": -5.3683625622072446,
      "state": {},
      "x_position": 201.6144946054022,
      "y_position": -398.33417674607273
    },
    {
      "ID": 86,
      "direction": -53.488749066607816,
      "state": {},
      "x_position": 48.279152399401831,
      "y_position": 38.765094077019292
    },
    {
      "ID": 87,
      "direction": -5.0759239902381292,
      "state": {},
      "x_position": 66.445374867690163,
      "y_position": -198.41755820404993
    },
    {
      "ID": 88,
      "direction": -9.4477471152478856,
      "state": {},
      "x_position": -240.01335913491079,
      "y_position": -629.39546071658788
    },
    {
      "ID": 89,
      "direction": 35.518907833465548,
      "state": {},
      "x_position": 110.8880715359908,
      "y_position": -83.488024774587601
    },
    {
      "ID": 90,
      "direction": -8.6213948615279961,
      "state": {},
      "x_position": -264.61142458234315,
      "y_position": -92.786240153793045
    },
    {
      "ID": 91,
      "direction": 13.330344563232813,
      "state": {},
      "x_position": -216.08940819421065,
      "y_position": -525.16473699661196
    },
    {
      "ID": 92,
      "direction": -9.2673500332420797,
      "state": {},
      "x_position": -452.17111492212422,
      "y_position": -53.36461032502698
    },
    {
      "ID": 93,
      "direction": -32.585019139956408,
      "state": {},
      "x_position": -215.13999085979154,
      "y_position": -355.10368183388454
    },
    {
      "ID": 94,
      "direction": 21.506706005953497,
      "state": {},
      "x_position": -88.833153431397875,
      "y_position": -428.12813710112385
    },
    {
      "ID": 95,
      "direction": 27.295422394313761,
      "state": {},
      "x_position": -358.20059956022163,
      "y_position": -437.10773184801639
    },
    {
      "ID": 96,
      "direction": 24.023785156969446,
      "state": {},
      "x_position": 147.17204243691666,
      "y_position": -69.530735857401751
    },
    {
      "ID": 97,
      "direction": 28.040878635647175,
      "state": {},
      "x_position": -209.54996722582749,
      "y_position": -139.41987578284508
    },
    {
      "ID": 98,
      "direction": 3.8818910001131712,
      "state": {},
      "x_position": -102.17793785805324,
      "y_position": -390.71361745933456
    },
    {
      "ID": 99,
      "direction": -5.2142591290578508,
      "state": {},
      "x_position": -344.48918773690986,
      "y_position": -101.74011306326101
    },
    {
      "ID": 100,
      "direction": -61.764009885707658,
      "state": {},
      "x_position": -228.59288803372687,
      "y_position": -388.47217784455341
    },
    {
      "ID": 101,
      "direction": -3.2149144573153912,
      "state": {},
      "x_position": 128.7902577496327,
      "y_position": 91.280990203705244
    },
    {
      "ID": 102,
      "direction": 34.236500940694427,
      "state": {},
      "x_position": -287.93467571265779,
      "y_position": -285.90388765148867
    },
    {
      "ID": 103,
      "direction": -33.056240499310412,
      "state": {},
      "x_position": -39.108414418982129,
      "y_position": 184.99821797697501
    },
    {
      "ID": 104,
      "direction": 73.723057513905317,
      "state": {},
      "x_position": -630.25850439801536,
      "y_position": 299.84179842050554
    },
    {
      "ID": 105,
      "direction": 8.5578811996733073,
      "state": {},
      "x_position": -445.52870643844329,
      "y_position": 30.083028937522368
    },
    {
      "ID": 106,
      "direction": -19.014918158570239,
      "state": {},
      "x_position": -120.73255795374888,
      "y_position": 206.99123019656125
    },
    {
      "ID": 107,
      "direction": -1.4396530039181092,
      "state": {},
      "x_position": -0.33334345461957327,
      "y_position": 520.81878386587357
    },
    {
      "ID": 108,
      "direction": 22.132442123837244,
      "state": {},
      "x_position": 21.794441543500838,
      "y_position": 315.27580551744046
    },
    {
      "ID": 109,
      "direction": -79.448172844303841,
      "state": {},
      "x_position": 160.89278541774652,
      "y_position": 114.07677691555119
    },
    {
      "ID": 110,
      "direction": 47.793672823936987,
      "state": {},
      "x_position": 326.19479295708061,
      "y_position": 376.41931591172943
    },
    {
      "ID": 111,
      "direction": -14.067000092244029,
      "state": {},
      "x_position": 605.73079146217583,
      "y_position": 242.45082422075683
    },
    {
      "ID": 112,
      "direction": 25.08717767346943,
      "state": {},
      "x_position": 195.79385326448744,
      "y_position": 347.90480853855746
    },
    {
      "ID": 113,
      "direction": -7.0361210521947761,
      "state": {},
      "x_position": 511.95977214047201,
      "y_position": -28.13410103971734
    },
    {
      "ID": 114,
      "direction": -6.7605668245234671,
      "state": {},
      "x_position": 437.74527433947628,
      "y_position": 243.35637684032861
    },
    {
      "ID": 115,
      "direction": 42.246745257309598,
      "state": {},
      "x_position": 215.36227211769881,
      "y_position": 25.403295175817682
    },
    {
      "ID": 116,
      "direction": -73.029564652559074,
      "state": {},
      "x_position": 408.60745120882746,
      "y_position": 59.463221035166484
    },
    {
      "ID": 117,
      "direction": -54.948798188030025,
      "state": {},
      "x_position": -17.580194400981195,
      "y_position": -57.089980487620039
    },
    {
      "ID": 118,
      "direction": 10.003117883019026,
      "state": {},
      "x_position": 10.864558298223127,
      "y_position": 62.752493671970186
    },
    {
      "ID": 119,
      "direction": 10.108790425074082,
      "state": {},
      "x_position": 254.61151315986686,
      "y_position": -254.80287452787778
    },
    {
      "ID": 120,
      "direction": -49.438256566655141,
      "state": {},
      "x_position": 293.66958186919902,
      "y_position": 9.3682941515257863
    },
    {
      "ID": 121,
      "direction": -58.166428517595463,
      "state": {},
      "x_position": 61.207208435525871,
      "y_position": 84.776180024212707
    },
    {
      "ID": 122,
      "direction": 12.027549275305507,
      "state": {},
      "x_position": -126.77163079524732,
      "y_position": -545.32489716820078
    },
    {
      "ID": 123,
      "direction": -30.749754348713619,
      "state": {},
      "x_position": 15.285609109889101,
      "y_position": -93.521520105003759
    },
    {
      "ID": 124,
      "direction": 13.35525933034906,
      "state": {},
      "x_position": -118.25777725841166,
      "y_position": -158.97753811833599
    },
    {
      "ID": 125,
      "direction": 0.38813627074859625,
      "state": {},
      "x_position": 495.40708165604013,
      "y_position": -390.58194026062608
    },
    {
      "ID": 126,
      "direction": 60.405395586219846,
      "state": {},
      "x_position": 51.178033645178999,
      "y_position": -163.43366266507309
    },
    {
      "ID": 127,
      "direction": 64.086671875755869,
      "state": {},
      "x_position": 194.9354483848914,
      "y_position": -205.29896715592119
    },
    {
      "ID": 128,
      "direction": 20.403332793812858,
      "state": {},
      "x_position": 387.37710222745773,
      "y_position": -338.41229644839615
    },
    {
      "ID": 129,
      "direction": 31.680744646441092,
      "state": {},
      "x_position": -50.666169056610435,
      "y_position": -165.12547802615802
    },
    {
      "ID": 130,
      "direction": -12.674031219114436,
      "state": {},
      "x_position": -20.668159693368949,
      "y_position": -147.70022646014104
    },
    {
      "ID": 131,
      "direction": 35.888352742441704,
      "state": {},
      "x_position": -0.56073765222705241,
      "y_position": -364.16575984936293
    },
    {
      "ID": 132,
      "direction": 25.517991680449022,
      "state": {},
      "x_position": 39.063134548288893,
      "y_position": -221.31815802663439
    },
    {
      "ID": 133,
      "direction": 7.4301510367842383,
      "state": {},
      "x_position": -433.86244433656753,
      "y_position": -127.89593253365187
    },
    {
      "ID": 134,
      "direction": -47.513912850154995,
      "state": {},
      "x_position": -181.96401996333029,
      "y_position": -523.35806408458552
    },
    {
      "ID": 135,
      "direction": -19.652818458304733,
      "state": {},
      "x_position": -268.32785249095645,
      "y_position": -254.24226964742638
    },
    {
      "ID": 136,
      "direction": 28.480816637604761,
      "state": {},
      "x_position": -284.21437474433151,
      "y_position": -623.11137779919409
    },
    {
      "ID": 137,
      "direction": -15.000282294176763,
      "state": {},
      "x_position": -437.31418651487388,
      "y_position": -335.00090635447094
    },
    {
      "ID": 138,
      "direction": 40.87510118711517,
      "state": {},
      "x_position": -223.18989492924555,
      "y_position": -271.5099183653781
    },
    {
      "ID": 139,
      "direction": 1.4064444697070577,
      "state": {},
      "x_position": -180.99265840804242,
      "y_position": 91.315557265476059
    },
    {
      "ID": 140,
      "direction": -46.548203947040541,
      "state": {},
      "x_position": -715.80664802358706,
      "y_position": 165.82188222460334
    },
    {
      "ID": 141,
      "direction": -1.6099611019848998,
      "state": {},
      "x_position": -137.22445925483103,
      "y_position": -22.685705753954245
    },
    {
      "ID": 142,
      "direction": 29.454615380376861,
      "state": {},
      "x_position": -373.60899832669423,
      "y_position": 21.105696225757093
    },
    {
      "ID": 143,
      "direction": -34.582160298808638,
      "state": {},
      "x_position": -373.6201047676613,
      "y_position": 375.97932445373658
    },
    {
      "ID": 144,
      "direction": 1.0449512821495857,
      "state": {},
      "x_position": -373.57555272164529,
      "y_position": 289.43734656952751
    },
    {
      "ID": 145,
      "direction": 13.446817706949918,
      "state": {},
      "x_position": -122.69534592682766,
      "y_position": 171.42581699976907
    },
    {
      "ID": 146,
      "direction": -14.583142859013517,
      "state": {},
      "x_position": -321.78107772254322,
      "y_position": 251.29911279167501
    },
    {
      "ID": 147,
      "direction": 7.4291698373008952,
      "state": {},
      "x_position": -198.87393124979195,
      "y_position": 522.99160604974963
    },
    {
      "ID": 148,
      "direction": 5.1969476213866095,
      "state": {},
      "x_position": -107.74003498936928,
      "y_position": 139.09947318155929
    },
    {
      "ID": 149,
      "direction": 0.65109945121893942,
      "state": {},
      "x_position": -63.683598668069806,
      "y_position": 471.66460481012786
    },
    {
      "ID": 150,
      "direction": 1.6223593258093465,
      "state": {},
      "x_position": -483.17487088300851,
      "y_position": 359.83651080582285
    },
    {
      "ID": 151,
      "direction": -21.510956558669868,
      "state": {},
      "x_position": 94.573925035850777,
      "y_position": 625.74586345184309
    },
    {
      "ID": 152,
      "direction": 9.1019502111044517,
      "state": {},
      "x_position": 76.985541186086166,
      "y_position": 401.15958246036587
    },
    {
      "ID": 153,
      "direction": -13.636063128401549,
      "state": {},
      "x_position": 323.67216067223274,
      "y_position": 109.5900031096883
    },
    {
      "ID": 154,
      "direction": -46.251479639895408,
      "state": {},
      "x_position": -34.833673944043092,
      "y_position": 100.95179533215165
    },
    {
      "ID": 155,
      "direction": 32.591629714693042,
      "state": {},
      "x_position": 109.02272842010798,
      "y_position": 275.52489053080291
    },
    {
      "ID": 156,
      "direction": -28.960290412550311,
      "state": {},
      "x_position": 223.84718209003117,
      "y_position": 157.54718758460206
    },
    {
      "ID": 157,
      "direction": -14.995782984463432,
      "state": {},
      "x_position": 432.96887083747157,
      "y_position": 85.693766022180242
    },
    {
      "ID": 158,
      "direction": 21.99172956136568,
      "state": {},
      "x_position": 354.31469045615336,
      "y_position": 269.9772062670711
    },
    {
      "ID": 159,
      "direction": -47.973375876416803,
      "state": {},
      "x_position": 582.6917881991792,
      "y_position": 196.46788511920775
    },
    {
      "ID": 160,
      "direction": -31.096611935368351,
      "state": {},
      "x_position": 81.289692744575959,
      "y_position": 236.99600417443835
    },
    {
      "ID": 161,
      "direction": -9.5117001479254384,
      "state": {},
      "x_position": 454.67985688177612,
      "y_position": 321.60759510653037
    },
    {
      "ID": 162,
      "direction": 39.521228612445242,
      "state": {},
      "x_position": 581.75998109508282,
      "y_position": 16.705495096478874
    },
    {
      "ID": 163,
      "direction": 14.74463570119854,
      "state": {},
      "x_position": 224.74006342571158,
      "y_position": -60.089869227417829
    },
    {
      "ID": 164,
      "direction": -40.392230658694515,
      "state": {},
      "x_position": 647.34338788548848,
      "y_position": 177.44415858863874
    },
    {
      "ID": 165,
      "direction": -8.2180308498647712,
      "state": {},
      "x_position": 488.91129315998614,
      "y_position": -499.33712667334402
    },
    {
      "ID": 166,
      "direction": -15.01952974923379,
      "state": {},
      "x_position": 277.37088334572167,
      "y_position": 168.77916494830447
    },
    {
      "ID": 167,
      "direction": 8.0053310586885011,
      "state": {},
      "x_position": -76.350049017938133,
      "y_position": -85.652338749563569
    },
    {
      "ID": 168,
      "direction": -19.432740540867467,
      "state": {},
      "x_position": 212.70740525900334,
      "y_position": -8.8539637979579808
    },
    {
      "ID": 169,
      "direction": -23.783090324530725,
      "state": {},
      "x_position": 313.72144253257534,
      "y_position": -441.51981166951737
    },
    {
      "ID": 170,
      "direction": -27.340659186806459,
      "state": {},
      "x_position": 517.92490514996302,
      "y_position": -363.08045503515723
    },
    {
      "ID": 171,
      "direction": 24.54789884061266,
      "state": {},
      "x_position": 300.00125911851995,
      "y_position": -375.34487156258501
    },
    {
      "ID": 172,
      "direction": 29.274081646712698,
      "state": {},
      "x_position": -49.45915568230545,
      "y_position": -306.37521543956467
    },
    {
      "ID": 173,
      "direction": -2.6618083607409653,
      "state": {},
      "x_position": 154.11019934459898,
      "y_position": -326.69132311919435
    },
    {
      "ID": 174,
      "direction": 21.989062176940333,
      "state": {},
      "x_position": 149.49831723471107,
      "y_position": -417.32837342553626
    },
    {
      "ID": 175,
      "direction": 6.6853923161473956,
      "state": {},
      "x_position": 72.388273936877098,
      "y_position": -549.13406567663026
    },
    {
      "ID": 176,
      "direction": -35.65372488420627,
      "state": {},
      "x_position": 38.975773508336289,
      "y_position": -538.41402668238447
    },
    {
      "ID": 177,
      "direction": 27.778694110762245,
      "state": {},
      "x_position": 172.57428701853397,
      "y_position": -650.6584431454163
    },
    {
      "ID": 178,
      "direction": 8.7295388764751856,
      "state": {},
      "x_position": 348.57204223151757,
      "y_position": -82.55233238144524
    },
    {
      "ID": 179,
      "direction": 40.822842672918256,
      "state": {},
      "x_position": -119.77474312145276,
      "y_position": -310.71690822647076
    },
    {
      "ID": 180,
      "direction": 62.512919276454078,
      "state": {},
      "x_position": -268.41670990745001,
      "y_position": -324.57196289297104
    },
    {
      "ID": 181,
      "direction": -8.5685511248049,
      "state": {},
      "x_position": -525.22468657703268,
      "y_position": -512.90722320650161
    },
    {
      "ID": 182,
      "direction": 12.223579741250489,
      "state": {},
      "x_position": -381.93390771173307,
      "y_position": 170.0866139461597
    },
    {
      "ID": 183,
      "direction": -45.615213432348774,
      "state": {},
      "x_position": -733.88156758424111,
      "y_position": -23.227011668331322
    },
    {
      "ID": 184,
      "direction": -12.090050216667077,
      "state": {},
      "x_position": -53.588856550658583,
      "y_position": -539.20590778504061
    },
    {
      "ID": 185,
      "direction": 10.247194724388695,
      "state": {},
      "x_position": -549.50988208399338,
      "y_position": -487.0632038648447
    },
    {
      "ID": 186,
      "direction": -38.304735988827048,
      "state": {},
      "x_position": -304.4669734404024,
      "y_position": -429.36685228437341
    },
    {
      "ID": 187,
      "direction": 51.936621749430309,
      "state": {},
      "x_position": -514.06905623115949,
      "y_position": -160.06694582856315
    },
    {
      "ID": 188,
      "direction": 33.575082858854991,
      "state": {},
      "x_position": -346.86890649874391,
      "y_position": 84.533734887443956
    },
    {
      "ID": 189,
      "direction": -5.2612367667463289,
      "state": {},
      "x_position": -567.61786903556413,
      "y_position": -275.40331795501908
    },
    {
      "ID": 190,
      "direction": 8.6223751183406403,
      "state": {},
      "x_position": -264.24064771284873,
      "y_position": 159.07772122663786
    },
    {
      "ID": 191,
      "direction": -25.044689315765165,
      "state": {},
      "x_position": -331.54197300968968,
      "y_position": -62.772117559879518
    },
    {
      "ID": 192,
      "direction": 45.490399805150744,
      "state": {},
      "x_position": -656.41174724168297,
      "y_position": 276.37795194462717
    },
    {
      "ID": 193,
      "direction": -18.569296482550474,
      "state": {},
      "x_position": -129.30216951934165,
      "y_position": 272.68423936919316
    },
    {
      "ID": 194,
      "direction": -10.631541746288516,
      "state": {},
      "x_position": -196.84275299260767,
      "y_position": 322.15996706991888
    },
    {
      "ID": 195,
      "direction": 21.170536643985667,
      "state": {},
      "x_position": -167.4777322504053,
      "y_position": 125.05135581261453
    },
    {
      "ID": 196,
      "direction": 27.247683095358539,
      "state": {},
      "x_position": -403.46389498066446,
      "y_position": -71.721194335224396
    },
    {
      "ID": 197,
      "direction": 66.775330668528937,
      "state": {},
      "x_position": -457.19378377179174,
      "y_position": 337.14959785944171
    },
    {
      "ID": 198,
      "direction": -4.5650067339487634,
      "state": {},
      "x_position": 87.489926678657909,
      "y_position": 512.09397864180789
    },
    {
      "ID": 199,
      "direction": 79.107594798530357,
      "state": {},
      "x_position": -494.60185240896607,
      "y_position": 421.4184132107444
    },
    {
      "ID": 200,
      "direction": -63.566846326338862,
      "state": {},
      "x_position": 251.71616780048473,
      "y_position": 439.99351417539248
    },
    {
      "ID": 201,
      "direction": -49.756041090824361,
      "state": {},
      "x_position": -258.28248656275258,
      "y_position": 355.76161408761158
    },
    {
      "ID": 202,
      "direction": -25.911699632494496,
      "state": {},
      "x_position": -405.36845366874422,
      "y_position": 496.33887831091226
    },
    {
      "ID": 203,
      "direction": 18.487197935332649,
      "state": {},
      "x_position": -240.25439832132369,
      "y_position": 384.85815285129991
    },
    {
      "ID": 204,
      "direction": 8.5725127868756967,
      "state": {},
      "x_position": -122.16045635554791,
      "y_position": 325.4602200676282
    },
    {
      "ID": 205,
      "direction": 35.336079654448277,
      "state": {},
      "x_position": 210.05435424668809,
      "y_position": 287.54301827451644
    },
    {
      "ID": 206,
      "direction": -11.831219197982239,
      "state": {},
      "x_position": 347.14838321060222,
      "y_position": 490.41951592548349
    },
    {
      "ID": 207,
      "direction": 26.832151046939838,
      "state": {},
      "x_position": 195.05083370743696,
      "y_position": 256.31682910229455
    },
    {
      "ID": 208,
      "direction": 25.193127965620008,
      "state": {},
      "x_position": 392.17345055026243,
      "y_position": 172.25984357411403
    },
    {
      "ID": 209,
      "direction": 15.901342119989543,
      "state": {},
      "x_position": 576.97603302697439,
      "y_position": 334.77720559460499
    },
    {
      "ID": 210,
      "direction": -37.066200820550982,
      "state": {},
      "x_position": 302.1828750743054,
      "y_position": 543.48534714672508
    },
    {
      "ID": 211,
      "direction": 39.229994423810098,
      "state": {},
      "x_position": 529.12471867498664,
      "y_position": 508.9537718274824
    },
    {
      "ID": 212,
      "direction": 18.54804998201206,
      "state": {},
      "x_position": 384.5241786882853,
      "y_position": 401.54775373004099
    },
    {
      "ID": 213,
      "direction": -15.732514156857961,
      "state": {},
      "x_position": 161.68345739015072,
      "y_position": -37.984108271790753
    },
    {
      "ID": 214,
      "direction": 55.572397041295829,
      "state": {},
      "x_position": 434.23116010861321,
      "y_position": 18.069225105452762
    },
    {
      "ID": 215,
      "direction": -26.865563271236656,
      "state": {},
      "x_position": 48.993633486889209,
      "y_position": -261.7715840321892
    },
    {
      "ID": 216,
      "direction": 25.865623512793508,
      "state": {},
      "x_position": 449.01614009309628,
      "y_position": -52.594186909797713
    },
    {
      "ID": 217,
      "direction": 29.436303569558479,
      "state": {},
      "x_position": 623.76839281157947,
      "y_position": -119.32543221023865
    },
    {
      "ID": 218,
      "direction": 12.516023688827524,
      "state": {},
      "x_position": 42.061496196753005,
      "y_position": -8.2689785830645963
    },
    {
      "ID": 219,
      "direction": -66.904515302082118,
      "state": {},
      "x_position": 537.45392021096518,
      "y_position": -155.85789673405344
    },
    {
      "ID": 220,
      "direction": 14.204992627113214,
      "state": {},
      "x_position": 619.50144589560091,
      "y_position": -249.35121000419414
    },
    {
      "ID": 221,
      "direction": -42.330064519273506,
      "state": {},
      "x_position": 304.87360463258335,
      "y_position": -268.86218125316731
    },
    {
      "ID": 222,
      "direction": 31.353189472850993,
      "state": {},
      "x_position": 271.73332427000378,
      "y_position": -455.52030718899573
    },
    {
      "ID": 223,
      "direction": -24.914910832664869,
      "state": {},
      "x_position": 243.90967557156247,
      "y_position": -350.33453618558667
    },
    {
      "ID": 224,
      "direction": -71.871880112486053,
      "state": {},
      "x_position": -9.4296001665113298,
      "y_position": -238.37133420606622
    },
    {
      "ID": 225,
      "direction": 47.598516890374441,
      "state": {},
      "x_position": 321.04081690534747,
      "y_position": -321.99523133706037
    },
    {
      "ID": 226,
      "direction": 18.301147114518564,
      "state": {},
      "x_position": 464.15488813613058,
      "y_position": -559.99438866857361
    },
    {
      "ID": 227,
      "direction": 15.553848603899283,
      "state": {},
      "x_position": 56.502286401875509,
      "y_position": -674.40753607938689
    },
    {
      "ID": 228,
      "direction": -30.052157388287529,
      "state": {},
      "x_position": 532.31669639432971,
      "y_position": -222.40192201799692
    },
    {
      "ID": 229,
      "direction": -36.965600536808466,
      "state": {},
      "x_position": 200.26103920501251,
      "y_position": -304.26651511233672
    },
    {
      "ID": 230,
      "direction": -20.661888130413381,
      "state": {},
      "x_position": 58.828969468614552,
      "y_position": -417.18454477552677
    },
    {
      "ID": 231,
      "direction": 43.588890817446746,
      "state": {},
      "x_position": 39.924932363743565,
      "y_position": -303.32625410937925
    },
    {
      "ID": 232,
      "direction": 8.4589185485237515,
      "state": {},
      "x_position": -45.845574059737409,
      "y_position": -440.84493549974411
    },
    {
      "ID": 233,
      "direction": -21.655500952442438,
      "state": {},
      "x_position": 192.71567960254748,
      "y_position": -270.13430258601022
    },
    {
      "ID": 234,
      "direction": -22.663535196752356,
      "state": {},
      "x_position": -405.62223270840667,
      "y_position": -553.60309247610462
    },
    {
      "ID": 235,
      "direction": -13.260252646922025,
      "state": {},
      "x_position": -22.710299193595162,
      "y_position": -475.68000280451224
    },
    {
      "ID": 236,
      "direction": 0.60040018540347884,
      "state": {},
      "x_position": -324.98592641978451,
      "y_position": -561.04228476466437
    },
    {
      "ID": 237,
      "direction": 7.8518488057533826,
      "state": {},
      "x_position": -187.18005899361785,
      "y_position": -392.7360916129258
    },
    {
      "ID": 238,
      "direction": -32.56063307201174,
      "state": {},
      "x_position": -93.819781134857379,
      "y_position": -270.80618013972003
    },
    {
      "ID": 239,
      "direction": -33.325979279161878,
      "state": {},
      "x_position": -500.34923881341479,
      "y_position": -317.94957527436958
    },
    {
      "ID": 240,
      "direction": -21.843669210999529,
      "state": {},
      "x_position": -635.11561200433175,
      "y_position": -362.42196825171214
    },
    {
      "ID": 241,
      "direction": -10.337090339120664,
      "state": {},
      "x_position": -306.91001627350295,
      "y_position": -336.50569811211977
    },
    {
      "ID": 242,
      "direction": 48.914315043252536,
      "state": {},
      "x_position": -494.85346897356396,
      "y_position": -130.07926231980596
    },
    {
      "ID": 243,
      "direction": 6.0992215976160784,
      "state": {},
      "x_position": -607.38411096006189,
      "y_position": -383.5126786723244
    },
    {
      "ID": 244,
      "direction": -0.87084875957757957,
      "state": {},
      "x_position": -327.90939443292308,
      "y_position": -465.65322536439322
    },
    {
      "ID": 245,
      "direction": 19.963040340462676,
      "state": {},
      "x_position": -571.33757022351119,
      "y_position": -203.85926165536895
    },
    {
      "ID": 246,
      "direction": -5.2005432024508043,
      "state": {},
      "x_position": -194.65194510374775,
      "y_position": 16.177096001080692
    },
    {
      "ID": 247,
      "direction": 43.000467126350109,
      "state": {},
      "x_position": -419.32880822707824,
      "y_position": 402.68819198820347
    },
    {
      "ID": 248,
      "direction": 26.525115313749637,
      "state": {},
      "x_position": -645.74313670336153,
      "y_position": 10.611110903121723
    },
    {
      "ID": 249,
      "direction": -71.477237781941596,
      "state": {},
      "x_position": -372.7340386194781,
      "y_position": 324.65187081969589
    },
    {
      "ID": 250,
      "direction": -17.799567653000356,
      "state": {},
      "x_position": -252.46175354430932,
      "y_position": -157.55688470696319
    },
    {
      "ID": 251,
      "direction": -9.3993956567624029,
      "state": {},
      "x_position": -295.80043376468467,
      "y_position": -14.364121938662844
    },
    {
      "ID": 252,
      "direction": -22.185889304544119,
      "state": {},
      "x_position": -664.61347877379342,
      "y_position": 309.60224070294282
    },
    {
      "ID": 253,
      "direction": -4.4098694727128844,
      "state": {},
      "x_position": -21.660546867587126,
      "y_position": 494.01533686407316
    },
    {
      "ID": 254,
      "direction": 43.896305433771481,
      "state": {},
      "x_position": -361.27932023545151,
      "y_position": 472.50810453905746
    },
    {
      "ID": 255,
      "direction": -4.7109424987393025,
      "state": {},
      "x_position": -504.09068691157199,
      "y_position": 280.21564583132414
    },
    {
      "ID": 256,
      "direction": 41.45957768074301,
      "state": {},
      "x_position": -212.8839617858618,
      "y_position": 252.39350466864485
    },
    {
      "ID": 257,
      "direction": 4.7844915752372685,
      "state": {},
      "x_position": -287.94937420373248,
      "y_position": 229.17140399999224
    },
    {
      "ID": 258,
      "direction": 68.533715246294236,
      "state": {},
      "x_position": -231.16659612508931,
      "y_position": 573.65552963345715
    },
    {
      "ID": 259,
      "direction": 35.118738439970272,
      "state": {},
      "x_position": -255.45741576307611,
      "y_position": 658.25766128623548
    },
    {
      "ID": 260,
      "direction": -35.085307437120214,
      "state": {},
      "x_position": 216.75712566388296,
      "y_position": 419.91448571641524
    },
    {
      "ID": 261,
      "direction": -40.861693507665343,
      "state": {},
      "x_position": 62.487681409534844,
      "y_position": 566.23922153536626
    },
    {
      "ID": 262,
      "direction": 22.382398130325011,
      "state": {},
      "x_position": 123.99555587778211,
      "y_position": 418.73578867612952
    },
    {
      "ID": 263,
      "direction": -21.827683454842635,
      "state": {},
      "x_position": 544.04026434210891,
      "y_position": 391.81203194307591
    },
    {
      "ID": 264,
      "direction": 11.080403568023129,
      "state": {},
      "x_position": 529.99112030793253,
      "y_position": -119.82202708273417
    },
    {
      "ID": 265,
      "direction": 68.4190863315944,
      "state": {},
      "x_position": 228.78716561110528,
      "y_position": 122.54887030867155
    },
    {
      "ID": 266,
      "direction": 16.580510733690101,
      "state": {},
      "x_position": -258.66048283400681,
      "y_position": 524.20232257479097
    },
    {
      "ID": 267,
      "direction": -19.677492856238089,
      "state": {},
      "x_position": 387.11876478586419,
      "y_position": 593.99443215949054
    },
    {
      "ID": 268,
      "direction": 20.737744085359576,
      "state": {},
      "x_position": 486.27975314876198,
      "y_position": 548.85065055426651
    },
    {
      "ID": 269,
      "direction": 49.617209662499796,
      "state": {},
      "x_position": 505.65280394227801,
      "y_position": 377.81878682270417
    },
    {
      "ID": 270,
      "direction": -9.0004517659454848,
      "state": {},
      "x_position": 572.28263079060343,
      "y_position": 229.8736164577611
    },
    {
      "ID": 271,
      "direction": 4.6705635561183163,
      "state": {},
      "x_position": 213.61626964522549,
      "y_position": -120.65448342584679
    },
    {
      "ID": 272,
      "direction": -25.075310984544007,
      "state": {},
      "x_position": 647.85261608040867,
      "y_position": 346.7006651935298
    },
    {
      "ID": 273,
      "direction": 32.675941472012461,
      "state": {},
      "x_position": 494.39835982100465,
      "y_position": 182.64775643098554
    },
    {
      "ID": 274,
      "direction": 30.353815100565548,
      "state": {},
      "x_position": 688.38533034996669,
      "y_position": 144.88269939692185
    },
    {
      "ID": 275,
      "direction": 17.207802301609359,
      "state": {},
      "x_position": 707.60504339322267,
      "y_position": -9.8836741081146595
    },
    {
      "ID": 276,
      "direction": -15.337074267625246,
      "state": {},
      "x_position": 429.56119782857348,
      "y_position": -158.61740853710478
    },
    {
      "ID": 277,
      "direction": 21.454021379593989,
      "state": {},
      "x_position": 343.51285858579564,
      "y_position": -250.04206407155829
    },
    {
      "ID": 278,
      "direction": -46.790265455788685,
      "state": {},
      "x_position": 576.72667826906479,
      "y_position": -54.537873778960162
    },
    {
      "ID": 279,
      "direction": -12.749634170111696,
      "state": {},
      "x_position": 647.93501863897177,
      "y_position": -227.39261291308068
    },
    {
      "ID": 280,
      "direction": 10.337676978837465,
      "state": {},
      "x_position": 637.67783367353309,
      "y_position": 256.58279399172432
    },
    {
      "ID": 281,
      "direction": -28.759776593702192,
      "state": {},
      "x_position": 704.09135461127835,
      "y_position": -203.11885298798722
    },
    {
      "ID": 282,
      "direction": -10.178373334680087,
      "state": {},
      "x_position": 232.25664288012905,
      "y_position": -179.06468742063595
    },
    {
      "ID": 283,
      "direction": 85.893320189348827,
      "state": {},
      "x_position": 386.16562087534254,
      "y_position": -569.67644914465086
    },
    {
      "ID": 284,
      "direction": -84.288031854236905,
      "state": {},
      "x_position": 283.70984533604337,
      "y_position": -133.36540479433876
    },
    {
      "ID": 285,
      "direction": 6.0562239928283539,
      "state": {},
      "x_position": 468.97418073431157,
      "y_position": -180.46870370846239
    },
    {
      "ID": 286,
      "direction": -25.825305274837092,
      "state": {},
      "x_position": 570.30214968788755,
      "y_position": -133.68351526295797
    },
    {
      "ID": 287,
      "direction": 20.139398177009213,
      "state": {},
      "x_position": 242.24700537967158,
      "y_position": -394.60864912231204
    },
    {
      "ID": 288,
      "direction": -2.9891825504388692,
      "state": {},
      "x_position": 223.58102514526891,
      "y_position": -675.22093608752323
    },
    {
      "ID": 289,
      "direction": -0.23912903466060342,
      "state": {},
      "x_position": -156.42475164395904,
      "y_position": -407.77945269010473
    },
    {
      "ID": 290,
      "direction": 75.398231760538295,
      "state": {},
      "x_position": 231.80412673324386,
      "y_position": -317.57119638951758
    },
    {
      "ID": 291,
      "direction": 89.465637528400876,
      "state": {},
      "x_position": -281.01118258645675,
      "y_position": -559.17474299344053
    },
    {
      "ID": 292,
      "direction": 16.060185102757018,
      "state": {},
      "x_position": 9.9768553398406308,
      "y_position": -461.65633388991358
    },
    {
      "ID": 293,
      "direction": 11.634762439063604,
      "state": {},
      "x_position": -18.887675284559066,
      "y_position": -393.0044229166503
    },
    {
      "ID": 294,
      "direction": -39.564734586490459,
      "state": {},
      "x_position": -446.61603698240054,
      "y_position": -518.55080959617135
    },
    {
      "ID": 295,
      "direction": 14.044642035875086,
      "state": {},
      "x_position": -178.67688681051999,
      "y_position": -570.01133199982223
    },
    {
      "ID": 296,
      "direction": -38.190323948226549,
      "state": {},
      "x_position": -192.54236879367429,
      "y_position": -198.15064594705322
    },
    {
      "ID": 297,
      "direction": 5.145259101056368,
      "state": {},
      "x_position": -283.93741271901007,
      "y_position": -478.88535729647225
    },
    {
      "ID": 298,
      "direction": -63.560135004921896,
      "state": {},
      "x_position": -272.97000724751837,
      "y_position": -660.4575856172022
    },
    {
      "ID": 299,
      "direction": -49.792044482901517,
      "state": {},
      "x_position": -323.10036441984784,
      "y_position": -254.48491683411342
    },
    {
      "ID": 300,
      "direction": 48.399124565642644,
      "state": {},
      "x_position": -426.14824099690389,
      "y_position": -242.8673612260998
    },
    {
      "ID": 301,
      "direction": -33.589394774201942,
      "state": {},
      "x_position": -365.90493378718645,
      "y_position": 118.71448423027866
    },
    {
      "ID": 302,
      "direction": 33.238390272116867,
      "state": {},
      "x_position": -26.676418918982236,
      "y_position": -513.46986236997554
    },
    {
      "ID": 303,
      "direction": 7.3027179148583992,
      "state": {},
      "x_position": -375.96143147159665,
      "y_position": -290.55171616123016
    },
    {
      "ID": 304,
      "direction": 27.4939518203715,
      "state": {},
      "x_position": -281.74631554652859,
      "y_position": -136.93594391476321
    },
    {
      "ID": 305,
      "direction": -3.2954812800764408,
      "state": {},
      "x_position": -572.9724791365328,
      "y_position": 5.9806808125841338
    },
    {
      "ID": 306,
      "direction": 30.106071448149191,
      "state": {},
      "x_position": -222.67393241990513,
      "y_position": -175.46083134951147
    },
    {
      "ID": 307,
      "direction": 14.970016744485541,
      "state": {},
      "x_position": -667.92058011605752,
      "y_position": -195.89266111735753
    },
    {
      "ID": 308,
      "direction": -21.482137223016149,
      "state": {},
      "x_position": -248.38755095753635,
      "y_position": -123.0020664199394
    },
    {
      "ID": 309,
      "direction": -14.363698919158562,
      "state": {},
      "x_position": -580.5638957966645,
      "y_position": 351.29187210539038
    },
    {
      "ID": 310,
      "direction": 13.981853273330515,
      "state": {},
      "x_position": -307.95319229214914,
      "y_position": 85.823919842120759
    },
    {
      "ID": 311,
      "direction": 33.954667945399258,
      "state": {},
      "x_position": -674.58221999414172,
      "y_position": 30.986822222661019
    },
    {
      "ID": 312,
      "direction": -4.9567247986506331,
      "state": {},
      "x_position": -383.38093327140524,
      "y_position": 215.16174498764462
    },
    {
      "ID": 313,
      "direction": 4.7584755028130301,
      "state": {},
      "x_position": -465.32066334793728,
      "y_position": 273.81504994770603
    },
    {
      "ID": 314,
      "direction": 23.250893148210004,
      "state": {},
      "x_position": -332.14703990168312,
      "y_position": 292.24487028119404
    },
    {
      "ID": 315,
      "direction": 32.132864522092845,
      "state": {},
      "x_position": -451.05672222831834,
      "y_position": 195.02372037786813
    },
    {
      "ID": 316,
      "direction": -41.313035909742979,
      "state": {},
      "x_position": -336.68081066758259,
      "y_position": 215.14145003721555
    },
    {
      "ID": 317,
      "direction": 6.9167558889207381,
      "state": {},
      "x_position": -328.81776291687817,
      "y_position": 514.49299326057223
    },
    {
      "ID": 318,
      "direction": 4.00408865685454,
      "state": {},
      "x_position": -132.85140709349776,
      "y_position": 588.47822902063365
    },
    {
      "ID": 319,
      "direction": 85.012944674520085,
      "state": {},
      "x_position": -624.90517859347312,
      "y_position": 370.97886626694054
    },
    {
      "ID": 320,
      "direction": -36.307215887633298,
      "state": {},
      "x_position": -360.09940143212481,
      "y_position": 542.54086037033687
    },
    {
      "ID": 321,
      "direction": 18.1111208585985,
      "state": {},
      "x_position": -220.37203433493897,
      "y_position": 700.98494494780164
    },
    {
      "ID": 322,
      "direction": 48.899732386733341,
      "state": {},
      "x_position": 1.5784367039859966,
      "y_position": 286.86638060207235
    },
    {
      "ID": 323,
      "direction": -26.867883600591249,
      "state": {},
      "x_position": -173.76236334679396,
      "y_position": 548.23228621304224
    },
    {
      "ID": 324,
      "direction": 40.056976660589044,
      "state": {},
      "x_position": 29.380495904763091,
      "y_position": 579.65307239680021
    },
    {
      "ID": 325,
      "direction": -39.753007351818184,
      "state": {},
      "x_position": -122.42889675949536,
      "y_position": 653.57968419345241
    },
    {
      "ID": 326,
      "direction": -0.69123751000555345,
      "state": {},
      "x_position": 27.075829704536478,
      "y_position": 418.56900651498336
    },
    {
      "ID": 327,
      "direction": 29.116028455192279,
      "state": {},
      "x_position": 153.27331814286444,
      "y_position": 675.48081319410051
    },
    {
      "ID": 328,
      "direction": 24.671922775953579,
      "state": {},
      "x_position": 94.114826036513335,
      "y_position": 477.25873653686358
    },
    {
      "ID": 329,
      "direction": 63.992559827589993,
      "state": {},
      "x_position": -78.774262097850198,
      "y_position": 319.06936554201565
    },
    {
      "ID": 330,
      "direction": 4.2155816760115457,
      "state": {},
      "x_position": -215.44040720726858,
      "y_position": 408.70628232715973
    },
    {
      "ID": 331,
      "direction": 24.913956646491496,
      "state": {},
      "x_position": 126.32692506035869,
      "y_position": 611.73929529785687
    },
    {
      "ID": 332,
      "direction": 37.862493615442716,
      "state": {},
      "x_position": 312.13132505392628,
      "y_position": 603.87017635029281
    },
    {
      "ID": 333,
      "direction": 18.193758412521227,
      "state": {},
      "x_position": 448.37000925047096,
      "y_position": 287.32797436490722
    },
    {
      "ID": 334,
      "direction": -42.497344679965217,
      "state": {},
      "x_position": 245.93427822304875,
      "y_position": 561.93472688480404
    },
    {
      "ID": 335,
      "direction": -2.1735971035979942,
      "state": {},
      "x_position": 342.16369330141816,
      "y_position": 435.11080879432109
    },
    {
      "ID": 336,
      "direction": 79.164428744330991,
      "state": {},
      "x_position": 251.75826223918568,
      "y_position": 349.0861885380109
    },
    {
      "ID": 337,
      "direction": -15.745687527098646,
      "state": {},
      "x_position": 416.55520522815198,
      "y_position": 303.68889509478214
    },
    {
      "ID": 338,
      "direction": 23.299903067536604,
      "state": {},
      "x_position": 507.86647476268939,
      "y_position": 5.8861567869057971
    },
    {
      "ID": 339,
      "direction": -52.381231119229312,
      "state": {},
      "x_position": -24.718763771970217,
      "y_position": 257.57596269969906
    },
    {
      "ID": 340,
      "direction": -78.958485817213329,
      "state": {},
      "x_position": 666.53984904684933,
      "y_position": 102.89981470060681
    },
    {
      "ID": 341,
      "direction": -6.2601540847101438,
      "state": {},
      "x_position": 644.20725556684442,
      "y_position": 51.104717535917707
    },
    {
      "ID": 342,
      "direction": -54.46900246502581,
      "state": {},
      "x_position": 310.60147340816593,
      "y_position": 249.36996435513089
    },
    {
      "ID": 343,
      "direction": -6.1446392645720831,
      "state": {},
      "x_position": 326.68717402964285,
      "y_position": 23.25259233329616
    },
    {
      "ID": 344,
      "direction": -10.604924146288081,
      "state": {},
      "x_position": 609.0016693477038,
      "y_position": -215.57308787337146
    },
    {
      "ID": 345,
      "direction": 34.273268926510376,
      "state": {},
      "x_position": 412.57953436726615,
      "y_position": -58.973817715234375
    },
    {
      "ID": 346,
      "direction": -9.9554955847945976,
      "state": {},
      "x_position": 497.46138563396994,
      "y_position": -150.43539594058461
    },
    {
      "ID": 347,
      "direction": 11.907781964050685,
      "state": {},
      "x_position": 715.18933767310716,
      "y_position": -47.901621009255607
    },
    {
      "ID": 348,
      "direction": -10.778374508339736,
      "state": {},
      "x_position": 334.674129141756,
      "y_position": -354.97576343266064
    },
    {
      "ID": 349,
      "direction": -34.184505371759599,
      "state": {},
      "x_position": 607.96813140352151,
      "y_position": -296.30621847561133
    },
    {
      "ID": 350,
      "direction": 19.818757898234075,
      "state": {},
      "x_position": 396.86807289061164,
      "y_position": -118.19085716500216
    },
    {
      "ID": 351,
      "direction": 25.519012172260233,
      "state": {},
      "x_position": 565.79591168267382,
      "y_position": -457.40117868454104
    },
    {
      "ID": 352,
      "direction": 22.158913059000394,
      "state": {},
      "x_position": 389.80568010695237,
      "y_position": 207.70448223931419
    },
    {
      "ID": 353,
      "direction": 26.087544661762589,
      "state": {},
      "x_position": 446.85955148751106,
      "y_position": -281.34839644413864
    },
    {
      "ID": 354,
      "direction": 1.8400951503130614,
      "state": {},
      "x_position": 271.94541933671223,
      "y_position": -190.7985874465889
    },
    {
      "ID": 355,
      "direction": -7.344516854773488,
      "state": {},
      "x_position": 426.0107542282052,
      "y_position": -460.55125310112146
    },
    {
      "ID": 356,
      "direction": -63.982729725756435,
      "state": {},
      "x_position": 226.00643810813372,
      "y_position": -454.71410525728618
    },
    {
      "ID": 357,
      "direction": -5.5220961732806622,
      "state": {},
      "x_position": 191.92851479052678,
      "y_position": -431.79589253749043
    },
    {
      "ID": 358,
      "direction": 31.840857229605319,
      "state": {},
      "x_position": 425.54682062294955,
      "y_position": -310.08325519155613
    },
    {
      "ID": 359,
      "direction": -35.540346086314941,
      "state": {},
      "x_position": 247.41126743773287,
      "y_position": -546.13565772789991
    },
    {
      "ID": 360,
      "direction": 71.150490050983052,
      "state": {},
      "x_position": 320.43212467574295,
      "y_position": -639.11400992744859
    },
    {
      "ID": 361,
      "direction": 5.8968518608366374,
      "state": {},
      "x_position": 412.4821507112797,
      "y_position": -591.9332254717749
    },
    {
      "ID": 362,
      "direction": -21.764409373322437,
      "state": {},
      "x_position": -122.01623214358281,
      "y_position": -472.04922768474228
    },
    {
      "ID": 363,
      "direction": -4.2776060945858339,
      "state": {},
      "x_position": -187.7499154181773,
      "y_position": -651.02204689823691
    },
    {
      "ID": 364,
      "direction": 25.48921186441876,
      "state": {},
      "x_position": -90.445636440081117,
      "y_position": -577.40055516373775
    },
    {
      "ID": 365,
      "direction": -76.151452697169518,
      "state": {},
      "x_position": -161.86474324787986,
      "y_position": -493.75858759674571
    },
    {
      "ID": 366,
      "direction": 51.030343377619801,
      "state": {},
      "x_position": -275.99183809252651,
      "y_position": -514.3341834130531
    },
    {
      "ID": 367,
      "direction": -10.890379102206108,
      "state": {},
      "x_position": -436.67323411672811,
      "y_position": -276.6435821990965
    },
    {
      "ID": 368,
      "direction": 28.203749084959874,
      "state": {},
      "x_position": -484.98745022984815,
      "y_position": -551.18115812837516
    },
    {
      "ID": 369,
      "direction": -3.979599241603557,
      "state": {},
      "x_position": -421.94711779798757,
      "y_position": -453.22097460395014
    },
    {
      "ID": 370,
      "direction": -3.7640946073808852,
      "state": {},
      "x_position": -412.43204773968938,
      "y_position": -383.93662619873373
    },
    {
      "ID": 371,
      "direction": 45.183167888452836,
      "state": {},
      "x_position": -252.94023257368514,
      "y_position": -293.99955463525566
    },
    {
      "ID": 372,
      "direction": -70.153191331739862,
      "state": {},
      "x_position": -388.55534615214674,
      "y_position": -461.08768039372075
    },
    {
      "ID": 373,
      "direction": -52.132474371254986,
      "state": {},
      "x_position": -76.431050235548085,
      "y_position": 152.52458097302483
    },
    {
      "ID": 374,
      "direction": 12.759392165951308,
      "state": {},
      "x_position": -357.24946297086746,
      "y_position": -135.2489129333006
    },
    {
      "ID": 375,
      "direction": 12.805015174162364,
      "state": {},
      "x_position": -570.27491377522983,
      "y_position": -98.596687324184771
    },
    {
      "ID": 376,
      "direction": -46.802081351412006,
      "state": {},
      "x_position": -550.64226691056763,
      "y_position": -174.64773765798185
    },
    {
      "ID": 377,
      "direction": -55.590302895800946,
      "state": {},
      "x_position": -298.80165156893128,
      "y_position": -85.128379690764163
    },
    {
      "ID": 378,
      "direction": 14.543625244047877,
      "state": {},
      "x_position": -563.74518023810447,
      "y_position": 269.44734054136615
    },
    {
      "ID": 379,
      "direction": -28.293727913815243,
      "state": {},
      "x_position": -398.39549726498399,
      "y_position": -123.10964448117551
    },
    {
      "ID": 380,
      "direction": 15.751236231403443,
      "state": {},
      "x_position": -483.61259650738708,
      "y_position": 54.853043605038934
    },
    {
      "ID": 381,
      "direction": 2.72406387637756,
      "state": {},
      "x_position": -630.30563708366788,
      "y_position": -255.88961148852167
    },
    {
      "ID": 382,
      "direction": 62.681273658003818,
      "state": {},
      "x_position": -494.74717603348336,
      "y_position": -45.109819221042059
    },
    {
      "ID": 383,
      "direction": 66.302500413697814,
      "state": {},
      "x_position": -144.25611060230048,
      "y_position": 39.381802991590448
    },
    {
      "ID": 384,
      "direction": 22.559111917119132,
      "state": {},
      "x_position": -571.50970908506486,
      "y_position": 136.51632618112339
    },
    {
      "ID": 385,
      "direction": 33.77647423590259,
      "state": {},
      "x_position": -425.04657654059594,
      "y_position": 78.612333101331473
    },
    {
      "ID": 386,
      "direction": -10.63835116349615,
      "state": {},
      "x_position": -214.82200345749615,
      "y_position": 291.38778882857821
    },
    {
      "ID": 387,
      "direction": 37.863983264215129,
      "state": {},
      "x_position": -398.96053422027302,
      "y_position": 127.32686790645593
    },
    {
      "ID": 388,
      "direction": 27.43357266837932,
      "state": {},
      "x_position": -100.10167569408436,
      "y_position": 515.11820952755522
    },
    {
      "ID": 389,
      "direction": 9.285682490870542,
      "state": {},
      "x_position": -246.66390129533332,
      "y_position": 424.30243779200327
    },
    {
      "ID": 390,
      "direction": -45.718430929913474,
      "state": {},
      "x_position": -676.50824890273873,
      "y_position": 200.68063833673165
    },
    {
      "ID": 391,
      "direction": -17.917386071906417,
      "state": {},
      "x_position": -328.32391057050933,
      "y_position": 601.02676988302744
    },
    {
      "ID": 392,
      "direction": 30.156199490159082,
      "state": {},
      "x_position": -468.43361129869248,
      "y_position": 228.3202747430887
    },
    {
      "ID": 393,
      "direction": -13.384948975466436,
      "state": {},
      "x_position": -241.09514298219486,
      "y_position": 494.03677104039548
    },
    {
      "ID": 394,
      "direction": 42.430384971980821,
      "state": {},
      "x_position": -155.20099758037497,
      "y_position": 682.21508048857834
    },
    {
      "ID": 395,
      "direction": 2.9016787207293966,
      "state": {},
      "x_position": -127.91727542940663,
      "y_position": 381.49147894752304
    },
    {
      "ID": 396,
      "direction": -45.113019229862829,
      "state": {},
      "x_position": 95.366885008613238,
      "y_position": 555.94981533832174
    },
    {
      "ID": 397,
      "direction": -0.23482615706912879,
      "state": {},
      "x_position": -89.124430962587383,
      "y_position": 286.57091186316035
    },
    {
      "ID": 398,
      "direction": 24.486516084283874,
      "state": {},
      "x_position": 150.32619344046915,
      "y_position": 531.34498668295589
    },
    {
      "ID": 399,
      "direction": -39.61784029482007,
      "state": {},
      "x_position": 355.92161402597634,
      "y_position": 354.13064588597922
    },
    {
      "ID": 400,
      "direction": -4.0583094733893574,
      "state": {},
      "x_position": 99.748261074657194,
      "y_position": 589.91817420054508
    },
    {
      "ID": 401,
      "direction": 8.2759762514903219,
      "state": {},
      "x_position": 278.95330350487757,
      "y_position": 461.78894190838434
    },
    {
      "ID": 402,
      "direction": -19.821565044196092,
      "state": {},
      "x_position": 159.76806843411134,
      "y_position": 427.05666133847421
    },
    {
      "ID": 403,
      "direction": 2.1231669223953444,
      "state": {},
      "x_position": 272.23230863896981,
      "y_position": 498.97922311218019
    },
    {
      "ID": 404,
      "direction": -0.17663602324191663,
      "state": {},
      "x_position": -13.041128553136417,
      "y_position": 342.93291387822143
    },
    {
      "ID": 405,
      "direction": -4.7900649678360452,
      "state": {},
      "x_position": -27.320577128524153,
      "y_position": 544.95169654816561
    },
    {
      "ID": 406,
      "direction": -3.8863857931662942,
      "state": {},
      "x_position": -29.20217386221098,
      "y_position": 718.30651441704549
    },
    {
      "ID": 407,
      "direction": -20.804098139787971,
      "state": {},
      "x_position": 396.7023373672522,
      "y_position": 508.91912938170037
    },
    {
      "ID": 408,
      "direction": 9.7641487765087369,
      "state": {},
      "x_position": 304.81152074762554,
      "y_position": 638.60353403830175
    },
    {
      "ID": 409,
      "direction": -13.018524475087435,
      "state": {},
      "x_position": 617.25120695165208,
      "y_position": 158.82831024336699
    },
    {
      "ID": 410,
      "direction": -45.678600847013691,
      "state": {},
      "x_position": 529.15401215676559,
      "y_position": 182.62590166418198
    },
    {
      "ID": 411,
      "direction": 33.119848654593213,
      "state": {},
      "x_position": 443.5421013121296,
      "y_position": 52.782247960947075
    },
    {
      "ID": 412,
      "direction": -28.476731325631476,
      "state": {},
      "x_position": 507.9214880919094,
      "y_position": 41.205850346335588
    },
    {
      "ID": 413,
      "direction": -14.556883757976745,
      "state": {},
      "x_position": 626.57391200072027,
      "y_position": 81.113049179957343
    },
    {
      "ID": 414,
      "direction": 22.3859689348708,
      "state": {},
      "x_position": 538.74320893873016,
      "y_position": 216.61075940286804
    },
    {
      "ID": 415,
      "direction": -47.623796378245146,
      "state": {},
      "x_position": 587.43474919474272,
      "y_position": 51.162206886673168
    },
    {
      "ID": 416,
      "direction": -30.791692364683918,
      "state": {},
      "x_position": 493.8146631506882,
      "y_position": 248.35820786192699
    },
    {
      "ID": 417,
      "direction": -9.2514404302225728,
      "state": {},
      "x_position": 666.00255458379218,
      "y_position": -307.73351191675795
    },
    {
      "ID": 418,
      "direction": 39.736828506968763,
      "state": {},
      "x_position": 616.30441390364717,
      "y_position": 29.113598319668938
    },
    {
      "ID": 419,
      "direction": 14.915575742740593,
      "state": {},
      "x_position": 616.91956495813929,
      "y_position": -13.550748264997278
    },
    {
      "ID": 420,
      "direction": -40.265950470134086,
      "state": {},
      "x_position": 470.15842431251264,
      "y_position": 30.312519174296089
    },
    {
      "ID": 421,
      "direction": -8.1364104546812079,
      "state": {},
      "x_position": 553.19426626504617,
      "y_position": -92.600771535848992
    },
    {
      "ID": 422,
      "direction": -14.982569266636439,
      "state": {},
      "x_position": 481.74146674325806,
      "y_position": -315.62480504583607
    },
    {
      "ID": 423,
      "direction": 7.9976316883042848,
      "state": {},
      "x_position": 397.14795079140708,
      "y_position": -270.83356355116138
    },
    {
      "ID": 424,
      "direction": -19.48509988344254,
      "state": {},
      "x_position": 393.2175866729234,
      "y_position": -222.65485828588655
    },
    {
      "ID": 425,
      "direction": -23.880109520087366,
      "state": {},
      "x_position": 456.21633083142586,
      "y_position": -387.15645035187373
    },
    {
      "ID": 426,
      "direction": -27.482338235344667,
      "state": {},
      "x_position": 587.59808896846698,
      "y_position": -362.04025142762674
    },
    {
      "ID": 427,
      "direction": 24.361559939092896,
      "state": {},
      "x_position": 452.07642128626253,
      "y_position": -348.21996584672416
    },
    {
      "ID": 428,
      "direction": 29.043082892211359,
      "state": {},
      "x_position": 205.71297343618295,
      "y_position": -569.88061026179037
    },
    {
      "ID": 429,
      "direction": -2.9374669682238754,
      "state": {},
      "x_position": 438.35073822461607,
      "y_position": -537.68851425873959
    },
    {
      "ID": 430,
      "direction": 21.668743835685145,
      "state": {},
      "x_position": 348.33451298514785,
      "y_position": -448.49085285635476
    },
    {
      "ID": 431,
      "direction": 6.3204141219106402,
      "state": {},
      "x_position": 266.89752229788962,
      "y_position": -649.06413396424159
    },
    {
      "ID": 432,
      "direction": -36.063362931424415,
      "state": {},
      "x_position": 118.50698142166601,
      "y_position": -382.93489788002302
    },
    {
      "ID": 433,
      "direction": 27.324396210562355,
      "state": {},
      "x_position": 321.94812790013412,
      "y_position": -562.14611909602763
    },
    {
      "ID": 434,
      "direction": 8.2305810040844403,
      "state": {},
      "x_position": 140.19039884303854,
      "y_position": -190.93966070605916
    },
    {
      "ID": 435,
      "direction": 40.27922494754619,
      "state": {},
      "x_position": 231.03932759962629,
      "y_position": -508.86525318458598
    },
    {
      "ID": 436,
      "direction": 61.924641698100451,
      "state": {},
      "x_position": -66.372930242460029,
      "y_position": -698.87797389819059
    },
    {
      "ID": 437,
      "direction": -9.2014885561403474,
      "state": {},
      "x_position": 12.537266418515641,
      "y_position": -513.97463683806905
    },
    {
      "ID": 438,
      "direction": 11.545982456933473,
      "state": {},
      "x_position": 87.748314871185769,
      "y_position": -339.14386147459425
    },
    {
      "ID": 439,
      "direction": -46.337470569647046,
      "state": {},
      "x_position": -230.35917900624776,
      "y_position": -696.95317571673274
    },
    {
      "ID": 440,
      "direction": -12.856967206947228,
      "state": {},
      "x_position": 97.415899690686928,
      "y_position": -646.25574489498979
    },
    {
      "ID": 441,
      "direction": 9.4356176427084009,
      "state": {},
      "x_position": 21.788271690276673,
      "y_position": -647.1402230082266
    },
    {
      "ID": 442,
      "direction": -39.160973161907116,
      "state": {},
      "x_position": 118.30125776194505,
      "y_position": -718.12647892385894
    },
    {
      "ID": 443,
      "direction": 51.035724484950116,
      "state": {},
      "x_position": -447.04431713368649,
      "y_position": -476.56479353478159
    },
    {
      "ID": 444,
      "direction": 32.629525502974666,
      "state": {},
      "x_position": -244.60574962297156,
      "y_position": -547.05283712553933
    },
    {
      "ID": 445,
      "direction": -6.2514542140272162,
      "state": {},
      "x_position": -421.66833883409862,
      "y_position": -584.9421261390255
    },
    {
      "ID": 446,
      "direction": 7.5874973412410309,
      "state": {},
      "x_position": -322.95513902646405,
      "y_position": -526.80328328324163
    },
    {
      "ID": 447,
      "direction": -26.124227184264921,
      "state": {},
      "x_position": -108.80760468589523,
      "y_position": -696.39062446283128
    },
    {
      "ID": 448,
      "direction": 44.366201845251339,
      "state": {},
      "x_position": -457.76345026035347,
      "y_position": -362.82873307931101
    },
    {
      "ID": 449,
      "direction": -19.738154772269102,
      "state": {},
      "x_position": -501.25661680835793,
      "y_position": -429.98263142895252
    },
    {
      "ID": 450,
      "direction": -11.84506012740729,
      "state": {},
      "x_position": -88.965668850238345,
      "y_position": -37.880265992953362
    },
    {
      "ID": 451,
      "direction": 19.912358171466746,
      "state": {},
      "x_position": -539.10295312369965,
      "y_position": -404.49336775377941
    },
    {
      "ID": 452,
      "direction": 25.944844531439472,
      "state": {},
      "x_position": -640.65485638388418,
      "y_position": -95.574702355140076
    },
    {
      "ID": 453,
      "direction": 65.427832013209127,
      "state": {},
      "x_position": -605.65774793170556,
      "y_position": -283.75707425827085
    },
    {
      "ID": 454,
      "direction": -5.9571654806681238,
      "state": {},
      "x_position": -618.12063746444176,
      "y_position": 115.71901876226734
    },
    {
      "ID": 455,
      "direction": 77.670775960410211,
      "state": {},
      "x_position": -661.13012542870683,
      "y_position": -161.26232825087578
    },
    {
      "ID": 456,
      "direction": -65.048325255858771,
      "state": {},
      "x_position": -580.11515579901527,
      "y_position": -36.628500927287838
    },
    {
      "ID": 457,
      "direction": -51.282180111743486,
      "state": {},
      "x_position": -713.43348197493913,
      "y_position": 131.75095901208911
    },
    {
      "ID": 458,
      "direction": -21.199309269278093,
      "state": {},
      "x_position": -600.27305103790343,
      "y_position": -67.121233252927581
    },
    {
      "ID": 459,
      "direction": 23.169797599067088,
      "state": {},
      "x_position": -551.02904686535135,
      "y_position": 48.594605161645021
    },
    {
      "ID": 460,
      "direction": 13.225321512709591,
      "state": {},
      "x_position": -480.32898287819006,
      "y_position": -208.84064253391247
    },
    {
      "ID": 461,
      "direction": 39.959097442379601,
      "state": {},
      "x_position": -467.50954440975471,
      "y_position": -20.093422085065964
    },
    {
      "ID": 462,
      "direction": -7.2379923479494321,
      "state": {},
      "x_position": -499.45552995679049,
      "y_position": 246.12061073011179
    },
    {
      "ID": 463,
      "direction": 31.395587003775592,
      "state": {},
      "x_position": -583.04840724554697,
      "y_position": 393.5343847948489
    },
    {
      "ID": 464,
      "direction": 29.726772984555211,
      "state": {},
      "x_position": -532.5457553428397,
      "y_position": 212.79294714599456
    },
    {
      "ID": 465,
      "direction": 20.405196193573627,
      "state": {},
      "x_position": -484.78530456678914,
      "y_position": 490.19214869734628
    },
    {
      "ID": 466,
      "direction": -32.592137684869407,
      "state": {},
      "x_position": -473.38941516282944,
      "y_position": 393.18771367164686
    },
    {
      "ID": 467,
      "direction": 43.674266629041718,
      "state": {},
      "x_position": -575.28545978204181,
      "y_position": 316.72836707569587
    },
    {
      "ID": 468,
      "direction": 22.962531294048574,
      "state": {},
      "x_position": -450.3202581963684,
      "y_position": 419.18144088227598
    },
    {
      "ID": 469,
      "direction": -11.347823723117346,
      "state": {},
      "x_position": -272.59185009528454,
      "y_position": 479.10794970031253
    },
    {
      "ID": 470,
      "direction": 59.927296626540965,
      "state": {},
      "x_position": -200.09622753485644,
      "y_position": 370.62441177755801
    },
    {
      "ID": 471,
      "direction": -22.540454564285515,
      "state": {},
      "x_position": -62.234879633154009,
      "y_position": 507.34005974174897
    },
    {
      "ID": 472,
      "direction": 30.160941341448748,
      "state": {},
      "x_position": -171.53712436890621,
      "y_position": 583.7314190491096
    },
    {
      "ID": 473,
      "direction": 33.701830519917074,
      "state": {},
      "x_position": -57.596788769528686,
      "y_position": 369.5785608205008
    },
    {
      "ID": 474,
      "direction": 16.75175976089097,
      "state": {},
      "x_position": 16.10220348801856,
      "y_position": 362.27365789923527
    },
    {
      "ID": 475,
      "direction": -62.698570167918511,
      "state": {},
      "x_position": -324.71066907006542,
      "y_position": 555.35615222302749
    },
    {
      "ID": 476,
      "direction": 18.381146882980218,
      "state": {},
      "x_position": 5.407770787990394,
      "y_position": 555.39457317827976
    },
    {
      "ID": 477,
      "direction": -38.183701141704219,
      "state": {},
      "x_position": -108.8021179776173,
      "y_position": 462.70333037663573
    },
    {
      "ID": 478,
      "direction": 29.186574403938486,
      "state": {},
      "x_position": 35.016721194984562,
      "y_position": 522.1357993066307
    },
    {
      "ID": 479,
      "direction": -27.117636064312364,
      "state": {},
      "x_position": 13.582933377516641,
      "y_position": 617.44650316157197
    },
    {
      "ID": 480,
      "direction": -74.110715566474155,
      "state": {},
      "x_position": -47.391457026803963,
      "y_position": 336.27267239279854
    },
    {
      "ID": 481,
      "direction": 45.323571214048691,
      "state": {},
      "x_position": 342.9842266085584,
      "y_position": 548.80000562102964
    },
    {
      "ID": 482,
      "direction": 15.990091245654497,
      "state": {},
      "x_position": 173.07656449463309,
      "y_position": 557.99482539694509
    },
    {
      "ID": 483,
      "direction": 13.206682512695586,
      "state": {},
      "x_position": 204.09616564069484,
      "y_position": 624.71384031365437
    },
    {
      "ID": 484,
      "direction": -32.435433582621371,
      "state": {},
      "x_position": 154.72616687777662,
      "y_position": 476.69283233292992
    },
    {
      "ID": 485,
      "direction": -39.384986953481068,
      "state": {},
      "x_position": 54.201459966035124,
      "y_position": 702.65761946167106
    },
    {
      "ID": 486,
      "direction": -23.117384784327836,
      "state": {},
      "x_position": 491.35059922754652,
      "y_position": 345.29881320587782
    },
    {
      "ID": 487,
      "direction": 41.097283941193758,
      "state": {},
      "x_position": 251.25893547497057,
      "y_position": 596.97983695155642
    },
    {
      "ID": 488,
      "direction": 5.9312014573806167,
      "state": {},
      "x_position": 472.75104006297414,
      "y_position": 430.73714698954291
    },
    {
      "ID": 489,
      "direction": -24.219328266856522,
      "state": {},
      "x_position": 235.82243487906231,
      "y_position": 317.68147865679009
    },
    {
      "ID": 490,
      "direction": -25.263472732574744,
      "state": {},
      "x_position": 543.06996958970012,
      "y_position": 356.71604577467269
    },
    {
      "ID": 491,
      "direction": -15.896300412534627,
      "state": {},
      "x_position": 405.69048748184611,
      "y_position": 430.01422674586354
    }
  ],
  "ticks": 21700
}